opentelemetry/ext/lightstep/__init__.py
opentelemetry/ext/lightstep/api_client.py
opentelemetry/ext/lightstep/reporter.py
opentelemetry/ext/lightstep/util.py
opentelemetry/ext/lightstep/version.py
opentelemetry/ext/lightstep/metrics/__init__.py
opentelemetry/ext/lightstep/protobuf/collector_pb2.py
opentelemetry/ext/lightstep/protobuf/metrics_pb2.py
opentelemetry_ext_lightstep-0.9b0.dist-info/LICENSE
opentelemetry_ext_lightstep-0.9b0.dist-info/METADATA
opentelemetry_ext_lightstep-0.9b0.dist-info/WHEEL
opentelemetry_ext_lightstep-0.9b0.dist-info/top_level.txt
opentelemetry_ext_lightstep-0.9b0.dist-info/RECORD
