Metadata-Version: 2.1
Name: opentelemetry-ext-lightstep
Version: 0.9b0
Summary: LightStep Exporter for OpenTelemetry
Home-page: https://github.com/lightstep/opentelemetry-exporter-python
Author: LightStep Authors
License: Apache-2.0
Platform: any
Classifier: Development Status :: 3 - Alpha
Classifier: Intended Audience :: Developers
Classifier: License :: OSI Approved :: Apache Software License
Classifier: Programming Language :: Python
Classifier: Programming Language :: Python :: 3
Classifier: Programming Language :: Python :: 3.4
Classifier: Programming Language :: Python :: 3.5
Classifier: Programming Language :: Python :: 3.6
Classifier: Programming Language :: Python :: 3.7
Requires-Python: >=3.4
Requires-Dist: backoff (~=1.10.0)
Requires-Dist: googleapis-common-protos (<2.0,>=1.5.3)
Requires-Dist: protobuf (<4.0,>3.7.1)
Requires-Dist: requests (<3.0,>=2.19)
Requires-Dist: opentelemetry-api (==0.9b0)
Requires-Dist: opentelemetry-sdk (==0.9b0)
Provides-Extra: test
Requires-Dist: httpretty (~=1.0.2) ; extra == 'test'
